[
  {
    "name": "Bulbizarre",
    "booster": "mewtwo",
    "cardNumber": 1
  },
  {
    "name": "Herbizarre",
    "booster": "mewtwo",
    "cardNumber": 2
  },
  {
    "name": "Florizarre",
    "booster": "mewtwo",
    "cardNumber": 3
  },
  {
    "name": "Florizarre",
    "booster": "mewtwo",
    "cardNumber": 4
  },
  {
    "name": "Chenipan",
    "booster": "pikachu",
    "cardNumber": 5
  },
  {
    "name": "Chrysacier",
    "booster": "pikachu",
    "cardNumber": 6
  },
  {
    "name": "Papilusion",
    "booster": "pikachu",
    "cardNumber": 7
  },
  {
    "name": "Aspicot",
    "booster": "mewtwo",
    "cardNumber": 8
  },
  {
    "name": "Coconfort",
    "booster": "mewtwo",
    "cardNumber": 9
  },
  {
    "name": "Dardargnan",
    "booster": "mewtwo",
    "cardNumber": 10
  },
  {
    "name": "Mystherbe",
    "booster": "dracaufeu",
    "cardNumber": 11
  },
  {
    "name": "Ortide",
    "booster": "dracaufeu",
    "cardNumber": 12
  },
  {
    "name": "Rafflesia",
    "booster": "dracaufeu",
    "cardNumber": 13
  },
  {
    "name": "Paras",
    "booster": "pikachu",
    "cardNumber": 14
  },
  {
    "name": "Parasect",
    "booster": "pikachu",
    "cardNumber": 15
  },
  {
    "name": "Mimitoss",
    "booster": "mewtwo",
    "cardNumber": 16
  },
  {
    "name": "A\u00e9romite",
    "booster": "mewtwo",
    "cardNumber": 17
  },
  {
    "name": "Ch\u00e9tiflor",
    "booster": "dracaufeu",
    "cardNumber": 18
  },
  {
    "name": "Boustiflor",
    "booster": "dracaufeu",
    "cardNumber": 19
  },
  {
    "name": "Empiflor",
    "booster": "dracaufeu",
    "cardNumber": 20
  },
  {
    "name": "Noeunoeuf",
    "booster": "dracaufeu",
    "cardNumber": 21
  },
  {
    "name": "Noadkoko",
    "booster": "dracaufeu",
    "cardNumber": 22
  },
  {
    "name": "Noadkoko",
    "booster": "dracaufeu",
    "cardNumber": 23
  },
  {
    "name": "Saquedeneu",
    "booster": "dracaufeu",
    "cardNumber": 24
  },
  {
    "name": "Ins\u00e9cateur",
    "booster": "mewtwo",
    "cardNumber": 25
  },
  {
    "name": "Scarabrute",
    "booster": "dracaufeu",
    "cardNumber": 26
  },
  {
    "name": "Doudouvet",
    "booster": "dracaufeu",
    "cardNumber": 27
  },
  {
    "name": "Farfaduvet",
    "booster": "dracaufeu",
    "cardNumber": 28
  },
  {
    "name": "Chlorobule",
    "booster": "dracaufeu",
    "cardNumber": 29
  },
  {
    "name": "Fragilady",
    "booster": "dracaufeu",
    "cardNumber": 30
  },
  {
    "name": "Cabriolaine",
    "booster": "dracaufeu",
    "cardNumber": 31
  },
  {
    "name": "Chevroum",
    "booster": "dracaufeu",
    "cardNumber": 32
  },
  {
    "name": "Salam\u00e8che",
    "booster": "dracaufeu",
    "cardNumber": 33
  },
  {
    "name": "Reptincel",
    "booster": "dracaufeu",
    "cardNumber": 34
  },
  {
    "name": "Dracaufeu",
    "booster": "dracaufeu",
    "cardNumber": 35
  },
  {
    "name": "Dracaufeu",
    "booster": "dracaufeu",
    "cardNumber": 36
  },
  {
    "name": "Goupix",
    "booster": "dracaufeu",
    "cardNumber": 37
  },
  {
    "name": "Feunard",
    "booster": "dracaufeu",
    "cardNumber": 38
  },
  {
    "name": "Caninos",
    "booster": "pikachu",
    "cardNumber": 39
  },
  {
    "name": "Arcanin",
    "booster": "pikachu",
    "cardNumber": 40
  },
  {
    "name": "Arcanin",
    "booster": "pikachu",
    "cardNumber": 41
  },
  {
    "name": "Ponyta",
    "booster": "dracaufeu",
    "cardNumber": 42
  },
  {
    "name": "Galopa",
    "booster": "dracaufeu",
    "cardNumber": 43
  },
  {
    "name": "Magmar",
    "booster": "dracaufeu",
    "cardNumber": 44
  },
  {
    "name": "Pyroli",
    "booster": "dracaufeu",
    "cardNumber": 45
  },
  {
    "name": "Sulfura",
    "booster": "dracaufeu",
    "cardNumber": 46
  },
  {
    "name": "Sulfura",
    "booster": "dracaufeu",
    "cardNumber": 47
  },
  {
    "name": "Aflamanoir",
    "booster": "dracaufeu",
    "cardNumber": 48
  },
  {
    "name": "Tritox",
    "booster": "mewtwo",
    "cardNumber": 49
  },
  {
    "name": "Malamandre",
    "booster": "mewtwo",
    "cardNumber": 50
  },
  {
    "name": "Grillepattes",
    "booster": "dracaufeu",
    "cardNumber": 51
  },
  {
    "name": "Scolocendre",
    "booster": "dracaufeu",
    "cardNumber": 52
  },
  {
    "name": "Carapuce",
    "booster": "pikachu",
    "cardNumber": 53
  },
  {
    "name": "Carabaffe",
    "booster": "pikachu",
    "cardNumber": 54
  },
  {
    "name": "Tortank",
    "booster": "pikachu",
    "cardNumber": 55
  },
  {
    "name": "Tortank",
    "booster": "pikachu",
    "cardNumber": 56
  },
  {
    "name": "Psykokwak",
    "booster": "dracaufeu",
    "cardNumber": 57
  },
  {
    "name": "Akwakwak",
    "booster": "dracaufeu",
    "cardNumber": 58
  },
  {
    "name": "Ptitard",
    "booster": "dracaufeu",
    "cardNumber": 59
  },
  {
    "name": "T\u00eatarte",
    "booster": "dracaufeu",
    "cardNumber": 60
  },
  {
    "name": "Tartard",
    "booster": "dracaufeu",
    "cardNumber": 61
  },
  {
    "name": "Tentacool",
    "booster": "mewtwo",
    "cardNumber": 62
  },
  {
    "name": "Tentacruel",
    "booster": "mewtwo",
    "cardNumber": 63
  },
  {
    "name": "Otaria",
    "booster": "pikachu",
    "cardNumber": 64
  },
  {
    "name": "Lamantine",
    "booster": "pikachu",
    "cardNumber": 65
  },
  {
    "name": "Kokiyas",
    "booster": "mewtwo",
    "cardNumber": 66
  },
  {
    "name": "Crustabri",
    "booster": "mewtwo",
    "cardNumber": 67
  },
  {
    "name": "Krabby",
    "booster": "mewtwo",
    "cardNumber": 68
  },
  {
    "name": "Krabboss",
    "booster": "mewtwo",
    "cardNumber": 69
  },
  {
    "name": "Hypotrempe",
    "booster": "pikachu",
    "cardNumber": 70
  },
  {
    "name": "Hypoc\u00e9an",
    "booster": "pikachu",
    "cardNumber": 71
  },
  {
    "name": "Poissir\u00e8ne",
    "booster": "pikachu",
    "cardNumber": 72
  },
  {
    "name": "Poissoroy",
    "booster": "pikachu",
    "cardNumber": 73
  },
  {
    "name": "Stari",
    "booster": "dracaufeu",
    "cardNumber": 74
  },
  {
    "name": "Staross",
    "booster": "dracaufeu",
    "cardNumber": 75
  },
  {
    "name": "Staross",
    "booster": "dracaufeu",
    "cardNumber": 76
  },
  {
    "name": "Magicarpe",
    "booster": "dracaufeu",
    "cardNumber": 77
  },
  {
    "name": "L\u00e9viator",
    "booster": "pikachu",
    "cardNumber": 78
  },
  {
    "name": "Lokhlass",
    "booster": "dracaufeu",
    "cardNumber": 79
  },
  {
    "name": "Aquali",
    "booster": "mewtwo",
    "cardNumber": 80
  },
  {
    "name": "Amonita",
    "booster": "pikachu",
    "cardNumber": 81
  },
  {
    "name": "Amonistar",
    "booster": "pikachu",
    "cardNumber": 82
  },
  {
    "name": "Artikodin",
    "booster": "mewtwo",
    "cardNumber": 83
  },
  {
    "name": "Artikodin",
    "booster": "mewtwo",
    "cardNumber": 84
  },
  {
    "name": "Couaneton",
    "booster": "dracaufeu",
    "cardNumber": 85
  },
  {
    "name": "Lakm\u00e9cygne",
    "booster": "dracaufeu",
    "cardNumber": 86
  },
  {
    "name": "Grenousse",
    "booster": "dracaufeu",
    "cardNumber": 87
  },
  {
    "name": "Cro\u00e2poral",
    "booster": "dracaufeu",
    "cardNumber": 88
  },
  {
    "name": "Amphinobi",
    "booster": "dracaufeu",
    "cardNumber": 89
  },
  {
    "name": "Concombaffe",
    "booster": "dracaufeu",
    "cardNumber": 90
  },
  {
    "name": "Denticrisse",
    "booster": "dracaufeu",
    "cardNumber": 91
  },
  {
    "name": "Frissonille",
    "booster": "dracaufeu",
    "cardNumber": 92
  },
  {
    "name": "Beldeneige",
    "booster": "dracaufeu",
    "cardNumber": 93
  },
  {
    "name": "Pikachu",
    "booster": "pikachu",
    "cardNumber": 94
  },
  {
    "name": "Raichu",
    "booster": "pikachu",
    "cardNumber": 95
  },
  {
    "name": "Pikachu",
    "booster": "pikachu",
    "cardNumber": 96
  },
  {
    "name": "Magn\u00e9ti",
    "booster": "pikachu",
    "cardNumber": 97
  },
  {
    "name": "Magn\u00e9ton",
    "booster": "pikachu",
    "cardNumber": 98
  },
  {
    "name": "Voltorbe",
    "booster": "pikachu",
    "cardNumber": 99
  },
  {
    "name": "\u00c9lectrode",
    "booster": "pikachu",
    "cardNumber": 100
  },
  {
    "name": "\u00c9lektek",
    "booster": "pikachu",
    "cardNumber": 101
  },
  {
    "name": "Voltali",
    "booster": "pikachu",
    "cardNumber": 102
  },
  {
    "name": "\u00c9lecthor",
    "booster": "pikachu",
    "cardNumber": 103
  },
  {
    "name": "\u00c9lecthor",
    "booster": "pikachu",
    "cardNumber": 104
  },
  {
    "name": "Z\u00e9bibron",
    "booster": "dracaufeu",
    "cardNumber": 105
  },
  {
    "name": "Z\u00e9blitz",
    "booster": "dracaufeu",
    "cardNumber": 106
  },
  {
    "name": "Anchwatt",
    "booster": "mewtwo",
    "cardNumber": 107
  },
  {
    "name": "Lamp\u00e9roie",
    "booster": "mewtwo",
    "cardNumber": 108
  },
  {
    "name": "Ohmassacre",
    "booster": "mewtwo",
    "cardNumber": 109
  },
  {
    "name": "Galvaran",
    "booster": "dracaufeu",
    "cardNumber": 110
  },
  {
    "name": "Iguolta",
    "booster": "dracaufeu",
    "cardNumber": 111
  },
  {
    "name": "Wattapik",
    "booster": "dracaufeu",
    "cardNumber": 112
  },
  {
    "name": "M\u00e9lof\u00e9e",
    "booster": "pikachu",
    "cardNumber": 113
  },
  {
    "name": "M\u00e9lodelfe",
    "booster": "pikachu",
    "cardNumber": 114
  },
  {
    "name": "Abra",
    "booster": "dracaufeu",
    "cardNumber": 115
  },
  {
    "name": "Kadabra",
    "booster": "dracaufeu",
    "cardNumber": 116
  },
  {
    "name": "Alakazam",
    "booster": "dracaufeu",
    "cardNumber": 117
  },
  {
    "name": "Ramoloss",
    "booster": "dracaufeu",
    "cardNumber": 118
  },
  {
    "name": "Flagadoss",
    "booster": "dracaufeu",
    "cardNumber": 119
  },
  {
    "name": "Fantominus",
    "booster": "mewtwo",
    "cardNumber": 120
  },
  {
    "name": "Spectrum",
    "booster": "mewtwo",
    "cardNumber": 121
  },
  {
    "name": "Ectoplasma",
    "booster": "mewtwo",
    "cardNumber": 122
  },
  {
    "name": "Ectoplasma",
    "booster": "mewtwo",
    "cardNumber": 123
  },
  {
    "name": "Soporifik",
    "booster": "pikachu",
    "cardNumber": 124
  },
  {
    "name": "Hypnomade",
    "booster": "pikachu",
    "cardNumber": 125
  },
  {
    "name": "M. Mime",
    "booster": "mewtwo",
    "cardNumber": 126
  },
  {
    "name": "Lippoutou",
    "booster": "mewtwo",
    "cardNumber": 127
  },
  {
    "name": "Mewtwo",
    "booster": "mewtwo",
    "cardNumber": 128
  },
  {
    "name": "Mewtwo",
    "booster": "mewtwo",
    "cardNumber": 129
  },
  {
    "name": "Tarsal",
    "booster": "mewtwo",
    "cardNumber": 130
  },
  {
    "name": "Kirlia",
    "booster": "mewtwo",
    "cardNumber": 131
  },
  {
    "name": "Gardevoir",
    "booster": "mewtwo",
    "cardNumber": 132
  },
  {
    "name": "Chovsourir",
    "booster": "dracaufeu",
    "cardNumber": 133
  },
  {
    "name": "Rhinolove",
    "booster": "dracaufeu",
    "cardNumber": 134
  },
  {
    "name": "Gringolem",
    "booster": "dracaufeu",
    "cardNumber": 135
  },
  {
    "name": "Golemastoc",
    "booster": "dracaufeu",
    "cardNumber": 136
  },
  {
    "name": "Sabelette",
    "booster": "dracaufeu",
    "cardNumber": 137
  },
  {
    "name": "Sablaireau",
    "booster": "dracaufeu",
    "cardNumber": 138
  },
  {
    "name": "Taupiqueur",
    "booster": "pikachu",
    "cardNumber": 139
  },
  {
    "name": "Triopikeur",
    "booster": "pikachu",
    "cardNumber": 140
  },
  {
    "name": "F\u00e9rosinge",
    "booster": "dracaufeu",
    "cardNumber": 141
  },
  {
    "name": "Colossinge",
    "booster": "dracaufeu",
    "cardNumber": 142
  },
  {
    "name": "Machoc",
    "booster": "dracaufeu",
    "cardNumber": 143
  },
  {
    "name": "Machopeur",
    "booster": "dracaufeu",
    "cardNumber": 144
  },
  {
    "name": "Mackogneur",
    "booster": "dracaufeu",
    "cardNumber": 145
  },
  {
    "name": "Mackogneur",
    "booster": "dracaufeu",
    "cardNumber": 146
  },
  {
    "name": "Racaillou",
    "booster": "pikachu",
    "cardNumber": 147
  },
  {
    "name": "Gravalanch",
    "booster": "pikachu",
    "cardNumber": 148
  },
  {
    "name": "Grolem",
    "booster": "pikachu",
    "cardNumber": 149
  },
  {
    "name": "Onix",
    "booster": "pikachu",
    "cardNumber": 150
  },
  {
    "name": "Osselait",
    "booster": "mewtwo",
    "cardNumber": 151
  },
  {
    "name": "Ossatueur",
    "booster": "mewtwo",
    "cardNumber": 152
  },
  {
    "name": "Ossatueur",
    "booster": "mewtwo",
    "cardNumber": 153
  },
  {
    "name": "Kicklee",
    "booster": "mewtwo",
    "cardNumber": 154
  },
  {
    "name": "Tygnon",
    "booster": "dracaufeu",
    "cardNumber": 155
  },
  {
    "name": "Rhinocorne",
    "booster": "mewtwo",
    "cardNumber": 156
  },
  {
    "name": "Rhinof\u00e9ros",
    "booster": "mewtwo",
    "cardNumber": 157
  },
  {
    "name": "Kabuto",
    "booster": "dracaufeu",
    "cardNumber": 158
  },
  {
    "name": "Kabutops",
    "booster": "dracaufeu",
    "cardNumber": 159
  },
  {
    "name": "Kungfouine",
    "booster": "pikachu",
    "cardNumber": 160
  },
  {
    "name": "Shaofouine",
    "booster": "pikachu",
    "cardNumber": 161
  },
  {
    "name": "Poulpaf",
    "booster": "dracaufeu",
    "cardNumber": 162
  },
  {
    "name": "Krakos",
    "booster": "dracaufeu",
    "cardNumber": 163
  },
  {
    "name": "Abo",
    "booster": "dracaufeu",
    "cardNumber": 164
  },
  {
    "name": "Arbok",
    "booster": "dracaufeu",
    "cardNumber": 165
  },
  {
    "name": "Nidoran\u2640",
    "booster": "pikachu",
    "cardNumber": 166
  },
  {
    "name": "Nidorina",
    "booster": "pikachu",
    "cardNumber": 167
  },
  {
    "name": "Nidoqueen",
    "booster": "pikachu",
    "cardNumber": 168
  },
  {
    "name": "Nidoran\u2642",
    "booster": "pikachu",
    "cardNumber": 169
  },
  {
    "name": "Nidorino",
    "booster": "pikachu",
    "cardNumber": 170
  },
  {
    "name": "Nidoking",
    "booster": "pikachu",
    "cardNumber": 171
  },
  {
    "name": "Nosferapti",
    "booster": "mewtwo",
    "cardNumber": 172
  },
  {
    "name": "Nosferalto",
    "booster": "mewtwo",
    "cardNumber": 173
  },
  {
    "name": "Tadmorv",
    "booster": "mewtwo",
    "cardNumber": 174
  },
  {
    "name": "Grotadmorv",
    "booster": "mewtwo",
    "cardNumber": 175
  },
  {
    "name": "Smogo",
    "booster": "mewtwo",
    "cardNumber": 176
  },
  {
    "name": "Smogogo",
    "booster": "mewtwo",
    "cardNumber": 177
  },
  {
    "name": "Mysdibule",
    "booster": "dracaufeu",
    "cardNumber": 178
  },
  {
    "name": "Scalpion",
    "booster": "dracaufeu",
    "cardNumber": 179
  },
  {
    "name": "Scalproie",
    "booster": "dracaufeu",
    "cardNumber": 180
  },
  {
    "name": "Meltan",
    "booster": "dracaufeu",
    "cardNumber": 181
  },
  {
    "name": "Melmetal",
    "booster": "dracaufeu",
    "cardNumber": 182
  },
  {
    "name": "Minidraco",
    "booster": "mewtwo",
    "cardNumber": 183
  },
  {
    "name": "Draco",
    "booster": "mewtwo",
    "cardNumber": 184
  },
  {
    "name": "Dracolosse",
    "booster": "mewtwo",
    "cardNumber": 185
  },
  {
    "name": "Roucool",
    "booster": "mewtwo",
    "cardNumber": 186
  },
  {
    "name": "Roucoups",
    "booster": "mewtwo",
    "cardNumber": 187
  },
  {
    "name": "Roucarnage",
    "booster": "mewtwo",
    "cardNumber": 188
  },
  {
    "name": "Rattata",
    "booster": "dracaufeu",
    "cardNumber": 189
  },
  {
    "name": "Rattatac",
    "booster": "dracaufeu",
    "cardNumber": 190
  },
  {
    "name": "Piafabec",
    "booster": "dracaufeu",
    "cardNumber": 191
  },
  {
    "name": "Rapasdepic",
    "booster": "dracaufeu",
    "cardNumber": 192
  },
  {
    "name": "Rondoudou",
    "booster": "pikachu",
    "cardNumber": 193
  },
  {
    "name": "Grodoudou",
    "booster": "pikachu",
    "cardNumber": 194
  },
  {
    "name": "Grodoudou",
    "booster": "pikachu",
    "cardNumber": 195
  },
  {
    "name": "Miaouss",
    "booster": "dracaufeu",
    "cardNumber": 196
  },
  {
    "name": "Persian",
    "booster": "dracaufeu",
    "cardNumber": 197
  },
  {
    "name": "Canarticho",
    "booster": "dracaufeu",
    "cardNumber": 198
  },
  {
    "name": "Doduo",
    "booster": "dracaufeu",
    "cardNumber": 199
  },
  {
    "name": "Dodrio",
    "booster": "dracaufeu",
    "cardNumber": 200
  },
  {
    "name": "Excelangue",
    "booster": "mewtwo",
    "cardNumber": 201
  },
  {
    "name": "Leveinard",
    "booster": "pikachu",
    "cardNumber": 202
  },
  {
    "name": "Kangourex",
    "booster": "dracaufeu",
    "cardNumber": 203
  },
  {
    "name": "Tauros",
    "booster": "dracaufeu",
    "cardNumber": 204
  },
  {
    "name": "M\u00e9tamorph",
    "booster": "mewtwo",
    "cardNumber": 205
  },
  {
    "name": "\u00c9voli",
    "booster": "dracaufeu",
    "cardNumber": 206
  },
  {
    "name": "\u00c9voli",
    "booster": "mewtwo",
    "cardNumber": 207
  },
  {
    "name": "\u00c9voli",
    "booster": "pikachu",
    "cardNumber": 208
  },
  {
    "name": "Porygon",
    "booster": "mewtwo",
    "cardNumber": 209
  },
  {
    "name": "Pt\u00e9ra",
    "booster": "mewtwo",
    "cardNumber": 210
  },
  {
    "name": "Ronflex",
    "cardNumber": 211
  },
  {
    "name": "Chinchidou",
    "booster": "dracaufeu",
    "cardNumber": 212
  },
  {
    "name": "Pashmilla",
    "booster": "dracaufeu",
    "cardNumber": 213
  },
  {
    "name": "Moumouton",
    "booster": "dracaufeu",
    "cardNumber": 214
  },
  {
    "name": "Moumouflon",
    "booster": "dracaufeu",
    "cardNumber": 215
  },
  {
    "name": "Fossile Nautile",
    "booster": "pikachu",
    "cardNumber": 216
  },
  {
    "name": "Fossile D\u00f4me",
    "booster": "dracaufeu",
    "cardNumber": 217
  },
  {
    "name": "Vieil Ambre",
    "booster": "mewtwo",
    "cardNumber": 218
  },
  {
    "name": "Erika",
    "booster": "dracaufeu",
    "cardNumber": 219
  },
  {
    "name": "Ondine",
    "booster": "pikachu",
    "cardNumber": 220
  },
  {
    "name": "Auguste",
    "booster": "dracaufeu",
    "cardNumber": 221
  },
  {
    "name": "Koga",
    "booster": "mewtwo",
    "cardNumber": 222
  },
  {
    "name": "Giovanni",
    "booster": "mewtwo",
    "cardNumber": 223
  },
  {
    "name": "Pierre",
    "booster": "pikachu",
    "cardNumber": 224
  },
  {
    "name": "Morgane",
    "booster": "dracaufeu",
    "cardNumber": 225
  },
  {
    "name": "Major Bob",
    "booster": "pikachu",
    "cardNumber": 226
  },
  {
    "name": "Bulbizarre",
    "booster": "mewtwo",
    "cardNumber": 227
  },
  {
    "name": "Ortide",
    "booster": "dracaufeu",
    "cardNumber": 228
  },
  {
    "name": "Scarabrute",
    "booster": "dracaufeu",
    "cardNumber": 229
  },
  {
    "name": "Salam\u00e8che",
    "booster": "dracaufeu",
    "cardNumber": 230
  },
  {
    "name": "Galopa",
    "booster": "dracaufeu",
    "cardNumber": 231
  },
  {
    "name": "Carapuce",
    "booster": "pikachu",
    "cardNumber": 232
  },
  {
    "name": "L\u00e9viator",
    "booster": "pikachu",
    "cardNumber": 233
  },
  {
    "name": "Lokhlass",
    "booster": "dracaufeu",
    "cardNumber": 234
  },
  {
    "name": "\u00c9lectrode",
    "booster": "pikachu",
    "cardNumber": 235
  },
  {
    "name": "Alakazam",
    "booster": "dracaufeu",
    "cardNumber": 236
  },
  {
    "name": "Ramoloss",
    "booster": "dracaufeu",
    "cardNumber": 237
  },
  {
    "name": "Taupiqueur",
    "booster": "pikachu",
    "cardNumber": 238
  },
  {
    "name": "Osselait",
    "booster": "mewtwo",
    "cardNumber": 239
  },
  {
    "name": "Nidoqueen",
    "booster": "pikachu",
    "cardNumber": 240
  },
  {
    "name": "Nidoking",
    "booster": "pikachu",
    "cardNumber": 241
  },
  {
    "name": "Nosferalto",
    "booster": "mewtwo",
    "cardNumber": 242
  },
  {
    "name": "Smogogo",
    "booster": "mewtwo",
    "cardNumber": 243
  },
  {
    "name": "Dracolosse",
    "booster": "mewtwo",
    "cardNumber": 244
  },
  {
    "name": "Roucarnage",
    "booster": "mewtwo",
    "cardNumber": 245
  },
  {
    "name": "Miaouss",
    "booster": "dracaufeu",
    "cardNumber": 246
  },
  {
    "name": "M\u00e9tamorph",
    "booster": "mewtwo",
    "cardNumber": 247
  },
  {
    "name": "\u00c9voli",
    "booster": "pikachu",
    "cardNumber": 248
  },
  {
    "name": "Porygon",
    "booster": "mewtwo",
    "cardNumber": 249
  },
  {
    "name": "Ronflex",
    "booster": "pikachu",
    "cardNumber": 250
  },
  {
    "name": "Florizarre",
    "booster": "mewtwo",
    "cardNumber": 251
  },
  {
    "name": "Noadkoko",
    "booster": "dracaufeu",
    "cardNumber": 252
  },
  {
    "name": "Dracaufeu",
    "booster": "dracaufeu",
    "cardNumber": 253
  },
  {
    "name": "Arcanin",
    "booster": "pikachu",
    "cardNumber": 254
  },
  {
    "name": "Sulfura",
    "booster": "dracaufeu",
    "cardNumber": 255
  },
  {
    "name": "Tortank",
    "booster": "pikachu",
    "cardNumber": 256
  },
  {
    "name": "Staross",
    "booster": "dracaufeu",
    "cardNumber": 257
  },
  {
    "name": "Artikodin",
    "booster": "mewtwo",
    "cardNumber": 258
  },
  {
    "name": "Pikachu",
    "booster": "pikachu",
    "cardNumber": 259
  },
  {
    "name": "\u00c9lecthor",
    "booster": "pikachu",
    "cardNumber": 260
  },
  {
    "name": "Ectoplasma",
    "booster": "mewtwo",
    "cardNumber": 261
  },
  {
    "name": "Mewtwo",
    "booster": "mewtwo",
    "cardNumber": 262
  },
  {
    "name": "Mackogneur",
    "booster": "dracaufeu",
    "cardNumber": 263
  },
  {
    "name": "Ossatueur",
    "booster": "mewtwo",
    "cardNumber": 264
  },
  {
    "name": "Grodoudou",
    "booster": "pikachu",
    "cardNumber": 265
  },
  {
    "name": "Erika",
    "booster": "dracaufeu",
    "cardNumber": 266
  },
  {
    "name": "Ondine",
    "booster": "pikachu",
    "cardNumber": 267
  },
  {
    "name": "Auguste",
    "booster": "dracaufeu",
    "cardNumber": 268
  },
  {
    "name": "Koga",
    "booster": "mewtwo",
    "cardNumber": 269
  },
  {
    "name": "Giovanni",
    "booster": "mewtwo",
    "cardNumber": 270
  },
  {
    "name": "Pierre",
    "booster": "pikachu",
    "cardNumber": 271
  },
  {
    "name": "Morgane",
    "booster": "dracaufeu",
    "cardNumber": 272
  },
  {
    "name": "Major Bob",
    "booster": "pikachu",
    "cardNumber": 273
  },
  {
    "name": "Sulfura",
    "booster": "dracaufeu",
    "cardNumber": 274
  },
  {
    "name": "Artikodin",
    "booster": "mewtwo",
    "cardNumber": 275
  },
  {
    "name": "\u00c9lecthor",
    "booster": "pikachu",
    "cardNumber": 276
  },
  {
    "name": "Ectoplasma",
    "booster": "mewtwo",
    "cardNumber": 277
  },
  {
    "name": "Mackogneur",
    "booster": "dracaufeu",
    "cardNumber": 278
  },
  {
    "name": "Grodoudou",
    "booster": "pikachu",
    "cardNumber": 279
  },
  {
    "name": "Dracaufeu",
    "booster": "dracaufeu",
    "cardNumber": 280
  },
  {
    "name": "Pikachu",
    "booster": "pikachu",
    "cardNumber": 281
  },
  {
    "name": "Mewtwo",
    "booster": "mewtwo",
    "cardNumber": 282
  },
  {
    "name": "Mew",
    "cardNumber": 283
  },
  {
    "name": "Dracaufeu",
    "booster": "dracaufeu",
    "cardNumber": 284
  },
  {
    "name": "Pikachu",
    "booster": "dracaufeu",
    "cardNumber": 285
  },
  {
    "name": "Mewtwo",
    "booster": "dracaufeu",
    "cardNumber": 286
  }
]
